MANIFEST.in
README.rst
setup.cfg
setup.py
dtool_irods/__init__.py
dtool_irods/storagebroker.py
dtool_irods.egg-info/PKG-INFO
dtool_irods.egg-info/SOURCES.txt
dtool_irods.egg-info/dependency_links.txt
dtool_irods.egg-info/entry_points.txt
dtool_irods.egg-info/requires.txt
dtool_irods.egg-info/top_level.txt