Metadata-Version: 1.1
Name: dtool-irods
Version: 0.5.1
Summary: Add iRODS support to dtool
Home-page: https://github.com/jic-dtool/dtool-irods
Author: Tjelvar Olsson
Author-email: tjelvar.olsson@jic.ac.uk
License: MIT
Download-URL: https://github.com/jic-dtool/dtool-irods/tarball/0.5.1
Platform: UNKNOWN
